# class 结构
```
ClassFile {
    u4			magic;
    u2			minor_version;
    u2			major_version;
    u2			constant_pool_count;
    cp_info		contant_pool[constant_pool_count – 1];
    u2			access_flags;
    u2			this_class;
    u2			super_class;
    u2			interfaces_count;
    u2			interfaces[interfaces_count];
    u2			fields_count;
    field_info		fields[fields_count];
    u2			methods_count;
    method_info		methods[methods_count];
    u2			attributes_count;
    attribute_info	attributes[attributes_count];
}
```

# 
```
➜  gc git:(master) ✗ javap -v -p -s -sysinfo -constants SimpleClass 
警告: 二进制文件SimpleClass包含heidsoft.gc.SimpleClass
Classfile /Users/heidsoft/Downloads/research/heidsoft-java/heidsoft-java-core/target/classes/heidsoft/gc/SimpleClass.class
  Last modified 2021-10-16; size 504 bytes
  MD5 checksum ebe97f17c3cf342767e143a3d2880fb6
  Compiled from "SimpleClass.java"
public class heidsoft.gc.SimpleClass
  minor version: 0
  major version: 52
  flags: ACC_PUBLIC, ACC_SUPER
Constant pool:
   #1 = Methodref          #6.#17         // java/lang/Object."<init>":()V
   #2 = Fieldref           #18.#19        // java/lang/System.out:Ljava/io/PrintStream;
   #3 = String             #20            // Hello
   #4 = Methodref          #21.#22        // java/io/PrintStream.println:(Ljava/lang/String;)V
   #5 = Class              #23            // heidsoft/gc/SimpleClass
   #6 = Class              #24            // java/lang/Object
   #7 = Utf8               <init>
   #8 = Utf8               ()V
   #9 = Utf8               Code
  #10 = Utf8               LineNumberTable
  #11 = Utf8               LocalVariableTable
  #12 = Utf8               this
  #13 = Utf8               Lheidsoft/gc/SimpleClass;
  #14 = Utf8               sayHello
  #15 = Utf8               SourceFile
  #16 = Utf8               SimpleClass.java
  #17 = NameAndType        #7:#8          // "<init>":()V
  #18 = Class              #25            // java/lang/System
  #19 = NameAndType        #26:#27        // out:Ljava/io/PrintStream;
  #20 = Utf8               Hello
  #21 = Class              #28            // java/io/PrintStream
  #22 = NameAndType        #29:#30        // println:(Ljava/lang/String;)V
  #23 = Utf8               heidsoft/gc/SimpleClass
  #24 = Utf8               java/lang/Object
  #25 = Utf8               java/lang/System
  #26 = Utf8               out
  #27 = Utf8               Ljava/io/PrintStream;
  #28 = Utf8               java/io/PrintStream
  #29 = Utf8               println
  #30 = Utf8               (Ljava/lang/String;)V
{
  public heidsoft.gc.SimpleClass();
    descriptor: ()V
    flags: ACC_PUBLIC
    Code:
      stack=1, locals=1, args_size=1
         0: aload_0
         1: invokespecial #1                  // Method java/lang/Object."<init>":()V
         4: return
      LineNumberTable:
        line 3: 0
      LocalVariableTable:
        Start  Length  Slot  Name   Signature
            0       5     0  this   Lheidsoft/gc/SimpleClass;

  public void sayHello();
    descriptor: ()V
    flags: ACC_PUBLIC
    Code:
      stack=2, locals=1, args_size=1
         0: getstatic     #2                  // Field java/lang/System.out:Ljava/io/PrintStream;
         3: ldc           #3                  // String Hello
         5: invokevirtual #4                  // Method java/io/PrintStream.println:(Ljava/lang/String;)V
         8: return
      LineNumberTable:
        line 6: 0
        line 7: 8
      LocalVariableTable:
        Start  Length  Slot  Name   Signature
            0       9     0  this   Lheidsoft/gc/SimpleClass;
}
SourceFile: "SimpleClass.java"

```